{
  "lines": [
    {
      "ahb_expression": "Muss",
      "conditions": null,
      "data_element": null,
      "guid": "d74338c5-0456-4d65-a739-b36145fbecbb",
      "index": 0,
      "name": null,
      "section_name": null,
      "segment_code": null,
      "segment_group_key": null,
      "segment_id": null,
      "value_pool_entry": null
    },
    {
      "ahb_expression": "Muss",
      "conditions": "",
      "data_element": null,
      "guid": "1b3686f2-2f28-48ff-a755-3d7fa3e7c0ea",
      "index": 1,
      "name": "",
      "section_name": "Nachrichten-Kopfsegment",
      "segment_code": "UNH",
      "segment_group_key": null,
      "segment_id": "00001",
      "value_pool_entry": null
    },
    {
      "ahb_expression": "X",
      "conditions": "",
      "data_element": "0062",
      "guid": "7686542d-79e1-40d0-a182-2f4bcee96325",
      "index": 2,
      "name": "Nachrichten-Referenznummer",
      "section_name": "Nachrichten-Kopfsegment",
      "segment_code": "UNH",
      "segment_group_key": null,
      "segment_id": "00001",
      "value_pool_entry": null
    },
    {
      "ahb_expression": "X",
      "conditions": "",
      "data_element": "0065",
      "guid": "57c0a17e-0d7f-49af-828e-69a6c53df338",
      "index": 3,
      "name": "Bestellantwort",
      "section_name": "Nachrichten-Kopfsegment",
      "segment_code": "UNH",
      "segment_group_key": null,
      "segment_id": "00001",
      "value_pool_entry": "ORDRSP"
    },
    {
      "ahb_expression": "X",
      "conditions": "",
      "data_element": "0052",
      "guid": "a1bbf6d3-e12f-4876-bb90-ecfbcbf113a6",
      "index": 4,
      "name": "Entwurfs-Version",
      "section_name": "Nachrichten-Kopfsegment",
      "segment_code": "UNH",
      "segment_group_key": null,
      "segment_id": "00001",
      "value_pool_entry": "D"
    },
    {
      "ahb_expression": "X",
      "conditions": "",
      "data_element": "0054",
      "guid": "2528b224-27e7-4c4e-9590-cb3136b6edef",
      "index": 5,
      "name": "Ausgabe 2010 - A",
      "section_name": "Nachrichten-Kopfsegment",
      "segment_code": "UNH",
      "segment_group_key": null,
      "segment_id": "00001",
      "value_pool_entry": "10A"
    },
    {
      "ahb_expression": "X",
      "conditions": "",
      "data_element": "0051",
      "guid": "e044ebd7-8281-4334-9dfc-503815a7eb99",
      "index": 6,
      "name": "UN/CEFACT",
      "section_name": "Nachrichten-Kopfsegment",
      "segment_code": "UNH",
      "segment_group_key": null,
      "segment_id": "00001",
      "value_pool_entry": "UN"
    },
    {
      "ahb_expression": "X",
      "conditions": "",
      "data_element": "0057",
      "guid": "58da7193-c605-4090-a191-52888699ca44",
      "index": 7,
      "name": "Versionsnummer derzugrundeliegendenBDEW-Nachrichtenbeschreibung",
      "section_name": "Nachrichten-Kopfsegment",
      "segment_code": "UNH",
      "segment_group_key": null,
      "segment_id": "00001",
      "value_pool_entry": "1.3"
    },
    {
      "ahb_expression": "Muss",
      "conditions": null,
      "data_element": null,
      "guid": "ee210a92-57b8-4f8d-bfec-17a20043d832",
      "index": 8,
      "name": null,
      "section_name": null,
      "segment_code": null,
      "segment_group_key": null,
      "segment_id": null,
      "value_pool_entry": null
    },
    {
      "ahb_expression": "Muss",
      "conditions": "",
      "data_element": null,
      "guid": "121a86dc-9a87-4859-bb40-5087f86075a8",
      "index": 9,
      "name": "",
      "section_name": "Beginn der Nachricht",
      "segment_code": "BGM",
      "segment_group_key": null,
      "segment_id": "00002",
      "value_pool_entry": null
    },
    {
      "ahb_expression": "X",
      "conditions": "",
      "data_element": "1001",
      "guid": "e4974f65-031a-4fe8-a2a9-a83f48dd2737",
      "index": 10,
      "name": "Allokationsliste (MMMA)",
      "section_name": "Beginn der Nachricht",
      "segment_code": "BGM",
      "segment_group_key": null,
      "segment_id": "00002",
      "value_pool_entry": "Z24"
    },
    {
      "ahb_expression": "X",
      "conditions": "",
      "data_element": "1004",
      "guid": "071af669-45f8-47cf-b8d6-944358c940d1",
      "index": 11,
      "name": "Dokumentennummer",
      "section_name": "Beginn der Nachricht",
      "segment_code": "BGM",
      "segment_group_key": null,
      "segment_id": "00002",
      "value_pool_entry": null
    },
    {
      "ahb_expression": "Muss",
      "conditions": null,
      "data_element": null,
      "guid": "41c66620-b9d0-4f09-90e1-a83baff26fe2",
      "index": 12,
      "name": null,
      "section_name": null,
      "segment_code": null,
      "segment_group_key": null,
      "segment_id": null,
      "value_pool_entry": null
    },
    {
      "ahb_expression": "Muss",
      "conditions": "",
      "data_element": null,
      "guid": "63691b43-eb4b-48a0-9235-e8368dd3bbda",
      "index": 13,
      "name": "",
      "section_name": "Nachrichtendatum",
      "segment_code": "DTM",
      "segment_group_key": null,
      "segment_id": "00003",
      "value_pool_entry": null
    },
    {
      "ahb_expression": "X",
      "conditions": "",
      "data_element": "2005",
      "guid": "00242ca7-2b97-4011-bf13-27c998859ab0",
      "index": 14,
      "name": "Dokumenten-/Nachrichtendatum/-zeit",
      "section_name": "Nachrichtendatum",
      "segment_code": "DTM",
      "segment_group_key": null,
      "segment_id": "00003",
      "value_pool_entry": "137"
    },
    {
      "ahb_expression": "X [931] [494]",
      "conditions": "[494] Das hier genannte Datum muss der Zeitpunkt sein, zu dem das Dokument erstellt wurde, oder ein Zeitpunkt, der davor liegt. \n[931] Format: ZZZ = +00",
      "data_element": "2380",
      "guid": "a185ec4a-2aa9-4314-aca5-592d43b5212b",
      "index": 15,
      "name": "Datum oder Uhrzeit oderZeitspanne, Wert",
      "section_name": "Nachrichtendatum",
      "segment_code": "DTM",
      "segment_group_key": null,
      "segment_id": "00003",
      "value_pool_entry": null
    },
    {
      "ahb_expression": "X",
      "conditions": "",
      "data_element": "2379",
      "guid": "fbea7747-2635-4256-941e-42a8a59938f4",
      "index": 16,
      "name": "CCYYMMDDHHMMZZZ",
      "section_name": "Nachrichtendatum",
      "segment_code": "DTM",
      "segment_group_key": null,
      "segment_id": "00003",
      "value_pool_entry": "303"
    },
    {
      "ahb_expression": "Muss",
      "conditions": null,
      "data_element": null,
      "guid": "065e7867-a382-4497-9ec4-b758401029a9",
      "index": 17,
      "name": null,
      "section_name": null,
      "segment_code": null,
      "segment_group_key": null,
      "segment_id": null,
      "value_pool_entry": null
    },
    {
      "ahb_expression": "Muss",
      "conditions": "",
      "data_element": null,
      "guid": "1be94705-848f-4200-8ecc-1a0f90c88945",
      "index": 18,
      "name": "",
      "section_name": "Abonnement",
      "segment_code": "IMD",
      "segment_group_key": null,
      "segment_id": "00007",
      "value_pool_entry": null
    },
    {
      "ahb_expression": "X",
      "conditions": "",
      "data_element": "7081",
      "guid": "e15d1f1c-43e7-4252-b40e-d34cd8ba688b",
      "index": 19,
      "name": "Start Abo",
      "section_name": "Abonnement",
      "segment_code": "IMD",
      "segment_group_key": null,
      "segment_id": "00007",
      "value_pool_entry": "Z01"
    },
    {
      "ahb_expression": "Muss",
      "conditions": null,
      "data_element": null,
      "guid": "340ee63f-e351-4378-bc14-e7e6344bb3ac",
      "index": 20,
      "name": null,
      "section_name": null,
      "segment_code": null,
      "segment_group_key": "SG1",
      "segment_id": null,
      "value_pool_entry": null
    },
    {
      "ahb_expression": "Muss",
      "conditions": "",
      "data_element": null,
      "guid": "0d0af27c-d619-4548-8dd1-7a9c203e0a06",
      "index": 21,
      "name": "",
      "section_name": null,
      "segment_code": null,
      "segment_group_key": "SG1",
      "segment_id": null,
      "value_pool_entry": null
    },
    {
      "ahb_expression": "Muss",
      "conditions": "",
      "data_element": null,
      "guid": "b6e22bd7-a95b-474a-b30f-3ddd26010f50",
      "index": 22,
      "name": "",
      "section_name": "Referenz Nachrichtennummer",
      "segment_code": "RFF",
      "segment_group_key": "SG1",
      "segment_id": "00009",
      "value_pool_entry": null
    },
    {
      "ahb_expression": "X",
      "conditions": "",
      "data_element": "1153",
      "guid": "86df309b-778b-4e54-9190-f80044c331cd",
      "index": 23,
      "name": "Auftragsnummer (Einkauf)",
      "section_name": "Referenz Nachrichtennummer",
      "segment_code": "RFF",
      "segment_group_key": "SG1",
      "segment_id": "00009",
      "value_pool_entry": "ON"
    },
    {
      "ahb_expression": "X [525]",
      "conditions": "[525] Hinweis: Wert aus BGM+Z24 DE1004 der ORDERS, mit der die Anforderung Allokationsliste erfolgt ist",
      "data_element": "1154",
      "guid": "4df8cece-2dc4-41b2-9705-e51f44210af0",
      "index": 24,
      "name": "Referenz Nachrichtennummer",
      "section_name": "Referenz Nachrichtennummer",
      "segment_code": "RFF",
      "segment_group_key": "SG1",
      "segment_id": "00009",
      "value_pool_entry": null
    },
    {
      "ahb_expression": "Muss",
      "conditions": null,
      "data_element": null,
      "guid": "eda708f9-90bf-43e8-afa0-148a7d0c9f32",
      "index": 25,
      "name": null,
      "section_name": null,
      "segment_code": null,
      "segment_group_key": "SG1",
      "segment_id": null,
      "value_pool_entry": null
    },
    {
      "ahb_expression": "Muss",
      "conditions": "",
      "data_element": null,
      "guid": "5cf958ab-8f9e-4caa-aaa3-eab30d1df413",
      "index": 26,
      "name": "",
      "section_name": null,
      "segment_code": null,
      "segment_group_key": "SG1",
      "segment_id": null,
      "value_pool_entry": null
    },
    {
      "ahb_expression": "Muss",
      "conditions": "",
      "data_element": null,
      "guid": "8a7e99c2-4fec-401d-9c9f-fee5a4594206",
      "index": 27,
      "name": "",
      "section_name": "Prüfidentifikator",
      "segment_code": "RFF",
      "segment_group_key": "SG1",
      "segment_id": "00012",
      "value_pool_entry": null
    },
    {
      "ahb_expression": "X",
      "conditions": "",
      "data_element": "1153",
      "guid": "60772b14-1f65-4f2e-94ac-a67ff2a21ceb",
      "index": 28,
      "name": "Prüfidentifikator",
      "section_name": "Prüfidentifikator",
      "segment_code": "RFF",
      "segment_group_key": "SG1",
      "segment_id": "00012",
      "value_pool_entry": "Z13"
    },
    {
      "ahb_expression": "X",
      "conditions": "",
      "data_element": "1154",
      "guid": "49d2756c-c675-428e-8bf7-b451106ce29d",
      "index": 29,
      "name": "Ablehnung Allokationsliste",
      "section_name": "Prüfidentifikator",
      "segment_code": "RFF",
      "segment_group_key": "SG1",
      "segment_id": "00012",
      "value_pool_entry": "19110"
    },
    {
      "ahb_expression": "Muss",
      "conditions": null,
      "data_element": null,
      "guid": "b3e97915-1c7a-42cc-a412-6fb322f1185e",
      "index": 30,
      "name": null,
      "section_name": null,
      "segment_code": null,
      "segment_group_key": "SG2",
      "segment_id": null,
      "value_pool_entry": null
    },
    {
      "ahb_expression": "Muss",
      "conditions": "",
      "data_element": null,
      "guid": "26c405da-848c-46e2-9374-be7a342d279e",
      "index": 31,
      "name": "",
      "section_name": null,
      "segment_code": null,
      "segment_group_key": "SG2",
      "segment_id": null,
      "value_pool_entry": null
    },
    {
      "ahb_expression": "Muss",
      "conditions": "",
      "data_element": null,
      "guid": "3f96c944-9d66-4bd0-b9ab-3e083436f2f7",
      "index": 32,
      "name": "",
      "section_name": "Einzelheiten zu einer Anpassung/Änderung",
      "segment_code": "AJT",
      "segment_group_key": "SG2",
      "segment_id": "00013",
      "value_pool_entry": null
    },
    {
      "ahb_expression": "X",
      "conditions": "",
      "data_element": "4465",
      "guid": "18548fb0-0bba-4217-b90d-a80e65d5427d",
      "index": 33,
      "name": "Code des Prüfschritts",
      "section_name": "Einzelheiten zu einer Anpassung/Änderung",
      "segment_code": "AJT",
      "segment_group_key": "SG2",
      "segment_id": "00013",
      "value_pool_entry": null
    },
    {
      "ahb_expression": "G_0001",
      "conditions": "",
      "data_element": "1082",
      "guid": "98e9b095-59aa-437b-8134-0cad4698c6ac",
      "index": 34,
      "name": "",
      "section_name": "Einzelheiten zu einer Anpassung/Änderung",
      "segment_code": "AJT",
      "segment_group_key": "SG2",
      "segment_id": "00013",
      "value_pool_entry": null
    },
    {
      "ahb_expression": "Muss",
      "conditions": null,
      "data_element": null,
      "guid": "3c872b7b-55aa-40e3-9c84-4c73f34e3af3",
      "index": 35,
      "name": null,
      "section_name": null,
      "segment_code": null,
      "segment_group_key": "SG3",
      "segment_id": null,
      "value_pool_entry": null
    },
    {
      "ahb_expression": "Muss",
      "conditions": "",
      "data_element": null,
      "guid": "5420d536-907f-43e8-9173-9a7721f804c6",
      "index": 36,
      "name": "",
      "section_name": null,
      "segment_code": null,
      "segment_group_key": "SG3",
      "segment_id": null,
      "value_pool_entry": null
    },
    {
      "ahb_expression": "Muss",
      "conditions": "",
      "data_element": null,
      "guid": "d546b677-a3d8-4aa7-ac98-4426da2c3bee",
      "index": 37,
      "name": "",
      "section_name": "MP-ID Absender",
      "segment_code": "NAD",
      "segment_group_key": "SG3",
      "segment_id": "00015",
      "value_pool_entry": null
    },
    {
      "ahb_expression": "MS",
      "conditions": "",
      "data_element": "3035",
      "guid": "adb4c980-0db5-4768-9369-aa0a8843b095",
      "index": 38,
      "name": "",
      "section_name": "MP-ID Absender",
      "segment_code": "NAD",
      "segment_group_key": "SG3",
      "segment_id": "00015",
      "value_pool_entry": "Nachrichtenaussteller bzw.-absender"
    },
    {
      "ahb_expression": "X [29]",
      "conditions": "[29] MP-ID nur aus Sparte Gas",
      "data_element": "3039",
      "guid": "e6e8cb34-e161-4f84-85a9-8768a5e845a9",
      "index": 39,
      "name": "MP-ID",
      "section_name": "MP-ID Absender",
      "segment_code": "NAD",
      "segment_group_key": "SG3",
      "segment_id": "00015",
      "value_pool_entry": null
    },
    {
      "ahb_expression": "X",
      "conditions": "",
      "data_element": "3055",
      "guid": "b16195bd-18eb-4311-8831-d8adf114d149",
      "index": 40,
      "name": "GS1",
      "section_name": "MP-ID Absender",
      "segment_code": "NAD",
      "segment_group_key": "SG3",
      "segment_id": "00015",
      "value_pool_entry": "9"
    },
    {
      "ahb_expression": "X",
      "conditions": "",
      "data_element": "3055",
      "guid": "c9126042-ebb0-499b-b235-659ed8f3c4a9",
      "index": 41,
      "name": "DE, DVGW Service &Consult GmbH",
      "section_name": "MP-ID Absender",
      "segment_code": "NAD",
      "segment_group_key": "SG3",
      "segment_id": null,
      "value_pool_entry": "332"
    },
    {
      "ahb_expression": "Kann",
      "conditions": null,
      "data_element": null,
      "guid": "23f0a317-dbe0-468b-928a-1c33cd6ea43d",
      "index": 42,
      "name": null,
      "section_name": null,
      "segment_code": null,
      "segment_group_key": "SG6",
      "segment_id": null,
      "value_pool_entry": null
    },
    {
      "ahb_expression": "Kann",
      "conditions": "",
      "data_element": null,
      "guid": "34b8ae25-5a08-4dea-aee4-115a594629e1",
      "index": 43,
      "name": "",
      "section_name": null,
      "segment_code": null,
      "segment_group_key": "SG6",
      "segment_id": null,
      "value_pool_entry": null
    },
    {
      "ahb_expression": "Muss",
      "conditions": "",
      "data_element": null,
      "guid": "482ed276-c7be-414b-9c34-e0c0acc72703",
      "index": 44,
      "name": "",
      "section_name": "Ansprechpartner",
      "segment_code": "CTA",
      "segment_group_key": "SG6",
      "segment_id": "00016",
      "value_pool_entry": null
    },
    {
      "ahb_expression": "IC",
      "conditions": "",
      "data_element": "3139",
      "guid": "2fa2a416-5204-4026-96b3-644bef813914",
      "index": 45,
      "name": "",
      "section_name": "Ansprechpartner",
      "segment_code": "CTA",
      "segment_group_key": "SG6",
      "segment_id": "00016",
      "value_pool_entry": null
    },
    {
      "ahb_expression": "X",
      "conditions": "",
      "data_element": "3412",
      "guid": "ecd75d32-67de-406a-b276-898f8ce7ff19",
      "index": 46,
      "name": "Kontakt",
      "section_name": "Ansprechpartner",
      "segment_code": "CTA",
      "segment_group_key": "SG6",
      "segment_id": "00016",
      "value_pool_entry": null
    },
    {
      "ahb_expression": null,
      "conditions": null,
      "data_element": null,
      "guid": "ddd4e81f-4244-45ee-9dcb-6db096304815",
      "index": 47,
      "name": null,
      "section_name": null,
      "segment_code": null,
      "segment_group_key": "SG6",
      "segment_id": null,
      "value_pool_entry": null
    },
    {
      "ahb_expression": "Muss",
      "conditions": null,
      "data_element": null,
      "guid": "bb9bcf20-3deb-4587-833d-8b564a74e173",
      "index": 48,
      "name": null,
      "section_name": null,
      "segment_code": null,
      "segment_group_key": "SG6",
      "segment_id": null,
      "value_pool_entry": null
    },
    {
      "ahb_expression": "Muss",
      "conditions": "",
      "data_element": null,
      "guid": "354ed30f-a179-436c-9227-dcdc88306abb",
      "index": 49,
      "name": "",
      "section_name": "Kommunikationsverbindung",
      "segment_code": "COM",
      "segment_group_key": "SG6",
      "segment_id": "00017",
      "value_pool_entry": null
    },
    {
      "ahb_expression": "X",
      "conditions": "",
      "data_element": "3148",
      "guid": "e1e2acbc-bdc7-4faf-b30d-9aaf5d8cf9c7",
      "index": 50,
      "name": "Kommunikationsadresse,Identifikation",
      "section_name": "Kommunikationsverbindung",
      "segment_code": "COM",
      "segment_group_key": "SG6",
      "segment_id": "00017",
      "value_pool_entry": null
    },
    {
      "ahb_expression": "X [1P0..1]",
      "conditions": "",
      "data_element": "3155",
      "guid": "2db306ac-0faf-4073-9d63-b93100ab223d",
      "index": 51,
      "name": "Elektronische Post",
      "section_name": "Kommunikationsverbindung",
      "segment_code": "COM",
      "segment_group_key": "SG6",
      "segment_id": "00017",
      "value_pool_entry": "EM"
    },
    {
      "ahb_expression": "X [1P0..1]",
      "conditions": "",
      "data_element": "3155",
      "guid": "1435b74f-1b8f-44c1-a3f1-594f3273cda3",
      "index": 52,
      "name": "Telefax",
      "section_name": "Kommunikationsverbindung",
      "segment_code": "COM",
      "segment_group_key": "SG6",
      "segment_id": null,
      "value_pool_entry": "FX"
    },
    {
      "ahb_expression": "X [1P0..1]",
      "conditions": "",
      "data_element": "3155",
      "guid": "23273382-9c60-4923-b686-d2bed3ddaadb",
      "index": 53,
      "name": "Telefon",
      "section_name": "Kommunikationsverbindung",
      "segment_code": "COM",
      "segment_group_key": "SG6",
      "segment_id": null,
      "value_pool_entry": "TE"
    },
    {
      "ahb_expression": "X [1P0..1]",
      "conditions": "",
      "data_element": "3155",
      "guid": "8afb9742-8d7f-4289-a4dd-346f5d98a8f8",
      "index": 54,
      "name": "weiteres Telefon",
      "section_name": "Kommunikationsverbindung",
      "segment_code": "COM",
      "segment_group_key": "SG6",
      "segment_id": null,
      "value_pool_entry": "AJ"
    },
    {
      "ahb_expression": "X [1P0..1]",
      "conditions": "",
      "data_element": "3155",
      "guid": "699069b0-dbec-455a-b13c-db74f6117529",
      "index": 55,
      "name": "Handy",
      "section_name": "Kommunikationsverbindung",
      "segment_code": "COM",
      "segment_group_key": "SG6",
      "segment_id": null,
      "value_pool_entry": "AL"
    },
    {
      "ahb_expression": "Muss",
      "conditions": null,
      "data_element": null,
      "guid": "d60f4eee-ca8b-46a0-823c-3820b9eb6b36",
      "index": 56,
      "name": null,
      "section_name": null,
      "segment_code": null,
      "segment_group_key": "SG3",
      "segment_id": null,
      "value_pool_entry": null
    },
    {
      "ahb_expression": "Muss",
      "conditions": "",
      "data_element": null,
      "guid": "0a67e124-4acc-4ba8-ab0e-30233946e095",
      "index": 57,
      "name": "",
      "section_name": null,
      "segment_code": null,
      "segment_group_key": "SG3",
      "segment_id": null,
      "value_pool_entry": null
    },
    {
      "ahb_expression": "Muss",
      "conditions": "",
      "data_element": null,
      "guid": "c86862eb-d6c4-4ace-a541-0653a7e2c534",
      "index": 58,
      "name": "",
      "section_name": "MP-ID Empfänger",
      "segment_code": "NAD",
      "segment_group_key": "SG3",
      "segment_id": "00018",
      "value_pool_entry": null
    },
    {
      "ahb_expression": "MR",
      "conditions": "",
      "data_element": "3035",
      "guid": "c285243c-2dd3-484a-aee6-a453b1d3bf03",
      "index": 59,
      "name": "",
      "section_name": "MP-ID Empfänger",
      "segment_code": "NAD",
      "segment_group_key": "SG3",
      "segment_id": "00018",
      "value_pool_entry": null
    },
    {
      "ahb_expression": "X [29]",
      "conditions": "[29] MP-ID nur aus Sparte Gas",
      "data_element": "3039",
      "guid": "19b8a9c4-4858-4cce-899d-16efbcccaec2",
      "index": 60,
      "name": "MP-ID",
      "section_name": "MP-ID Empfänger",
      "segment_code": "NAD",
      "segment_group_key": "SG3",
      "segment_id": "00018",
      "value_pool_entry": null
    },
    {
      "ahb_expression": "X",
      "conditions": "",
      "data_element": "3055",
      "guid": "a43bb5fa-3734-4c4d-95ec-4e5d036a3a7f",
      "index": 61,
      "name": "GS1",
      "section_name": "MP-ID Empfänger",
      "segment_code": "NAD",
      "segment_group_key": "SG3",
      "segment_id": "00018",
      "value_pool_entry": "9"
    },
    {
      "ahb_expression": "X",
      "conditions": "",
      "data_element": "3055",
      "guid": "26a80d9e-742b-405a-bde9-f2e43b28d83d",
      "index": 62,
      "name": "DE, DVGW Service &Consult GmbH",
      "section_name": "MP-ID Empfänger",
      "segment_code": "NAD",
      "segment_group_key": "SG3",
      "segment_id": null,
      "value_pool_entry": "332"
    },
    {
      "ahb_expression": "Muss",
      "conditions": null,
      "data_element": null,
      "guid": "4a57f413-b87c-4c28-951d-a0d127966151",
      "index": 63,
      "name": null,
      "section_name": null,
      "segment_code": null,
      "segment_group_key": null,
      "segment_id": null,
      "value_pool_entry": null
    },
    {
      "ahb_expression": "Muss",
      "conditions": "",
      "data_element": null,
      "guid": "45df16e2-a9e0-408e-9bc0-6412e28f2f4d",
      "index": 64,
      "name": "",
      "section_name": "Abschnitts-Kontrollsegment",
      "segment_code": "UNS",
      "segment_group_key": null,
      "segment_id": "00030",
      "value_pool_entry": null
    },
    {
      "ahb_expression": "S",
      "conditions": "",
      "data_element": "0081",
      "guid": "9c6bb1bb-81c7-4861-8f52-d629e7e7d33e",
      "index": 65,
      "name": "",
      "section_name": "Abschnitts-Kontrollsegment",
      "segment_code": "UNS",
      "segment_group_key": null,
      "segment_id": "00030",
      "value_pool_entry": "und Summenteil"
    },
    {
      "ahb_expression": "Muss",
      "conditions": null,
      "data_element": null,
      "guid": "a7541ff6-3d88-4c52-98bc-987b01bd9390",
      "index": 66,
      "name": null,
      "section_name": null,
      "segment_code": null,
      "segment_group_key": null,
      "segment_id": null,
      "value_pool_entry": null
    },
    {
      "ahb_expression": "Muss",
      "conditions": "",
      "data_element": null,
      "guid": "46bfb434-c978-4f37-93db-ce4efd7a7ea7",
      "index": 67,
      "name": "",
      "section_name": "Nachrichten-Endesegment",
      "segment_code": "UNT",
      "segment_group_key": null,
      "segment_id": "00034",
      "value_pool_entry": null
    },
    {
      "ahb_expression": "X",
      "conditions": "",
      "data_element": "0074",
      "guid": "1263d9eb-7672-4560-9d95-0c7226533faa",
      "index": 68,
      "name": "Anzahl der Segmente in einerNachricht",
      "section_name": "Nachrichten-Endesegment",
      "segment_code": "UNT",
      "segment_group_key": null,
      "segment_id": "00034",
      "value_pool_entry": null
    },
    {
      "ahb_expression": "X",
      "conditions": "",
      "data_element": "0062",
      "guid": "d007bae7-faa4-44c2-ab35-7f38de9b9474",
      "index": 69,
      "name": "Nachrichten-Referenznummer",
      "section_name": "Nachrichten-Endesegment",
      "segment_code": "UNT",
      "segment_group_key": null,
      "segment_id": "00034",
      "value_pool_entry": null
    }
  ],
  "meta": {
    "description": "ORDRSP Abl. der Anforderung",
    "direction": "NB an LF",
    "maus_version": "0.3.0",
    "pruefidentifikator": "19110"
  }
}
