{
  "lines": [
    {
      "ahb_expression": "Muss",
      "conditions": null,
      "data_element": null,
      "guid": "84f43936-6e91-472e-a9a1-ce9f411fcfd2",
      "index": 0,
      "name": null,
      "section_name": null,
      "segment_code": null,
      "segment_group_key": null,
      "segment_id": null,
      "value_pool_entry": null
    },
    {
      "ahb_expression": "Muss",
      "conditions": "",
      "data_element": null,
      "guid": "430f371e-36a4-41b0-849a-87eec75c6db8",
      "index": 1,
      "name": "",
      "section_name": "Nachrichten-Kopfsegment",
      "segment_code": "UNH",
      "segment_group_key": null,
      "segment_id": "00001",
      "value_pool_entry": null
    },
    {
      "ahb_expression": "X",
      "conditions": "",
      "data_element": "0062",
      "guid": "072a4b41-8a8d-4916-bf2c-d7d936eed983",
      "index": 2,
      "name": "Nachrichten-Referenznummer",
      "section_name": "Nachrichten-Kopfsegment",
      "segment_code": "UNH",
      "segment_group_key": null,
      "segment_id": null,
      "value_pool_entry": null
    },
    {
      "ahb_expression": "X",
      "conditions": "",
      "data_element": "0065",
      "guid": "4be1ad82-fbb0-4a5b-8cbc-eee22205dc60",
      "index": 3,
      "name": "Angebot",
      "section_name": "Nachrichten-Kopfsegment",
      "segment_code": "UNH",
      "segment_group_key": null,
      "segment_id": null,
      "value_pool_entry": "QUOTES"
    },
    {
      "ahb_expression": "X",
      "conditions": "",
      "data_element": "0052",
      "guid": "aa49fdbf-b2ad-4cd5-a585-8ce7432e7b78",
      "index": 4,
      "name": "Entwurfs-Version",
      "section_name": "Nachrichten-Kopfsegment",
      "segment_code": "UNH",
      "segment_group_key": null,
      "segment_id": null,
      "value_pool_entry": "D"
    },
    {
      "ahb_expression": "X",
      "conditions": "",
      "data_element": "0054",
      "guid": "4a8ebd7e-eadd-4e54-b4d4-a2e3dea51416",
      "index": 5,
      "name": "Ausgabe 2010 - A",
      "section_name": "Nachrichten-Kopfsegment",
      "segment_code": "UNH",
      "segment_group_key": null,
      "segment_id": null,
      "value_pool_entry": "10A"
    },
    {
      "ahb_expression": "X",
      "conditions": "",
      "data_element": "0051",
      "guid": "17efb782-6a59-4351-a379-8b8ee3600bc0",
      "index": 6,
      "name": "UN/CEFACT",
      "section_name": "Nachrichten-Kopfsegment",
      "segment_code": "UNH",
      "segment_group_key": null,
      "segment_id": null,
      "value_pool_entry": "UN"
    },
    {
      "ahb_expression": "X",
      "conditions": "",
      "data_element": "0057",
      "guid": "ac06fe05-7caf-4fd3-8d98-ab71ed01fa41",
      "index": 7,
      "name": "Versionsnummer derzugrundeliegendenBDEW-Nachrichtenbeschreibung",
      "section_name": "Nachrichten-Kopfsegment",
      "segment_code": "UNH",
      "segment_group_key": null,
      "segment_id": null,
      "value_pool_entry": "1.3"
    },
    {
      "ahb_expression": "Muss",
      "conditions": null,
      "data_element": null,
      "guid": "821caa17-fcc5-4061-a99d-5959e4c713a5",
      "index": 8,
      "name": null,
      "section_name": null,
      "segment_code": null,
      "segment_group_key": null,
      "segment_id": null,
      "value_pool_entry": null
    },
    {
      "ahb_expression": "Muss",
      "conditions": "",
      "data_element": null,
      "guid": "c8858665-96d8-4a84-9e3c-5ff88f1d1d9d",
      "index": 9,
      "name": "",
      "section_name": "Beginn der Nachricht",
      "segment_code": "BGM",
      "segment_group_key": null,
      "segment_id": "00002",
      "value_pool_entry": null
    },
    {
      "ahb_expression": "X",
      "conditions": "",
      "data_element": "1001",
      "guid": "1b870a1b-44ca-4c23-bfdd-e1352ff8c700",
      "index": 10,
      "name": "Abrechnung desMessstellenbetriebs vomMSB an den LF",
      "section_name": "Beginn der Nachricht",
      "segment_code": "BGM",
      "segment_group_key": null,
      "segment_id": null,
      "value_pool_entry": "Z29"
    },
    {
      "ahb_expression": "X",
      "conditions": "",
      "data_element": "1004",
      "guid": "48416c59-7c99-45d0-9798-ce048a85763e",
      "index": 11,
      "name": "Dokumentennummer",
      "section_name": "Beginn der Nachricht",
      "segment_code": "BGM",
      "segment_group_key": null,
      "segment_id": null,
      "value_pool_entry": null
    },
    {
      "ahb_expression": "Muss",
      "conditions": null,
      "data_element": null,
      "guid": "253480f8-713d-4246-91dd-d855fa768b10",
      "index": 12,
      "name": null,
      "section_name": null,
      "segment_code": null,
      "segment_group_key": null,
      "segment_id": null,
      "value_pool_entry": null
    },
    {
      "ahb_expression": "Muss",
      "conditions": "",
      "data_element": null,
      "guid": "0dc91def-479b-477d-8d5f-47e64029fecf",
      "index": 13,
      "name": "",
      "section_name": "Nachrichtendatum",
      "segment_code": "DTM",
      "segment_group_key": null,
      "segment_id": "00003",
      "value_pool_entry": null
    },
    {
      "ahb_expression": "X",
      "conditions": "",
      "data_element": "2005",
      "guid": "d1822875-3896-4535-8d33-575d770c62fb",
      "index": 14,
      "name": "Dokumenten-/Nachrichtendatum/-zeit",
      "section_name": "Nachrichtendatum",
      "segment_code": "DTM",
      "segment_group_key": null,
      "segment_id": null,
      "value_pool_entry": "137"
    },
    {
      "ahb_expression": "X [931] [494]",
      "conditions": "[494] Das hier genannte Datum muss der Zeitpunkt sein, zu dem das Dokument erstellt wurde, oder ein Zeitpunkt, der davor liegt. \n[931] Format: ZZZ = +00",
      "data_element": "2380",
      "guid": "418ee851-6ea3-4d86-90ce-63512400362b",
      "index": 15,
      "name": "Datum oder Uhrzeit oderZeitspanne, Wert",
      "section_name": "Nachrichtendatum",
      "segment_code": "DTM",
      "segment_group_key": null,
      "segment_id": null,
      "value_pool_entry": null
    },
    {
      "ahb_expression": "X",
      "conditions": "",
      "data_element": "2379",
      "guid": "4a187811-fe55-44cb-b42b-fc0ec5564c91",
      "index": 16,
      "name": "CCYYMMDDHHMMZZZ",
      "section_name": "Nachrichtendatum",
      "segment_code": "DTM",
      "segment_group_key": null,
      "segment_id": null,
      "value_pool_entry": "303"
    },
    {
      "ahb_expression": "Muss [27]",
      "conditions": null,
      "data_element": null,
      "guid": "a2997950-c15a-4253-b8ae-6b303a651637",
      "index": 17,
      "name": null,
      "section_name": null,
      "segment_code": null,
      "segment_group_key": null,
      "segment_id": null,
      "value_pool_entry": null
    },
    {
      "ahb_expression": "Muss [27]",
      "conditions": "[27] Wenn DTM+469 nicht vorhanden",
      "data_element": null,
      "guid": "8c32337f-464e-40fd-8b75-ea114013215b",
      "index": 18,
      "name": "",
      "section_name": "Ausführungsdatum",
      "segment_code": "DTM",
      "segment_group_key": null,
      "segment_id": "00005",
      "value_pool_entry": null
    },
    {
      "ahb_expression": "X",
      "conditions": "",
      "data_element": "2005",
      "guid": "8829011d-44e3-43d9-b453-ac5dc422fa3d",
      "index": 19,
      "name": "Ausführungsdatum/-zeit",
      "section_name": "Ausführungsdatum",
      "segment_code": "DTM",
      "segment_group_key": null,
      "segment_id": null,
      "value_pool_entry": "203"
    },
    {
      "ahb_expression": "X [UB1]",
      "conditions": "",
      "data_element": "2380",
      "guid": "067ce747-90d5-4b75-a93a-3c9b72c57371",
      "index": 20,
      "name": "Datum oder Uhrzeit oderZeitspanne, Wert",
      "section_name": "Ausführungsdatum",
      "segment_code": "DTM",
      "segment_group_key": null,
      "segment_id": null,
      "value_pool_entry": null
    },
    {
      "ahb_expression": "X",
      "conditions": "",
      "data_element": "2379",
      "guid": "68d65ef4-42df-4c7a-be6f-a88fbfce2d06",
      "index": 21,
      "name": "CCYYMMDDHHMMZZZ",
      "section_name": "Ausführungsdatum",
      "segment_code": "DTM",
      "segment_group_key": null,
      "segment_id": null,
      "value_pool_entry": "303"
    },
    {
      "ahb_expression": "Soll [26] ∧ [28] ∧ [29]",
      "conditions": null,
      "data_element": null,
      "guid": "5847249c-c25e-49f5-95f8-5d95b15b37e7",
      "index": 22,
      "name": null,
      "section_name": null,
      "segment_code": null,
      "segment_group_key": null,
      "segment_id": null,
      "value_pool_entry": null
    },
    {
      "ahb_expression": "Soll [26] ∧ [28] ∧ [29]",
      "conditions": "[26] Wenn DTM+203 nicht vorhanden \n[28] Wenn RFF+AAV vorhanden \n[29] Wenn DTM+469 in Anfrage (REQOTE) vorhanden war",
      "data_element": null,
      "guid": "65c4ef26-3d45-4d48-919f-023469a69025",
      "index": 23,
      "name": "",
      "section_name": "Beginn zum (nächstmöglichen Termin)",
      "segment_code": "DTM",
      "segment_group_key": null,
      "segment_id": "00006",
      "value_pool_entry": null
    },
    {
      "ahb_expression": "X",
      "conditions": "",
      "data_element": "2005",
      "guid": "45c5823f-6d57-4583-b398-2115a8fbcc50",
      "index": 24,
      "name": "Startdatum oder -zeitpunkt, frühestes/r",
      "section_name": "Beginn zum (nächstmöglichen Termin)",
      "segment_code": "DTM",
      "segment_group_key": null,
      "segment_id": null,
      "value_pool_entry": "469"
    },
    {
      "ahb_expression": "X [UB1]",
      "conditions": "",
      "data_element": "2380",
      "guid": "d89e0e91-563f-4858-85d1-e94d28a1ccaf",
      "index": 25,
      "name": "Datum oder Uhrzeit oderZeitspanne, Wert",
      "section_name": "Beginn zum (nächstmöglichen Termin)",
      "segment_code": "DTM",
      "segment_group_key": null,
      "segment_id": null,
      "value_pool_entry": null
    },
    {
      "ahb_expression": "X",
      "conditions": "",
      "data_element": "2379",
      "guid": "72f8fb03-b7ee-4093-ab9d-d67381a545d8",
      "index": 26,
      "name": "CCYYMMDDHHMMZZZ",
      "section_name": "Beginn zum (nächstmöglichen Termin)",
      "segment_code": "DTM",
      "segment_group_key": null,
      "segment_id": null,
      "value_pool_entry": "303"
    },
    {
      "ahb_expression": "Muss",
      "conditions": null,
      "data_element": null,
      "guid": "63bf15cd-6267-418a-a3ad-80c2c1839913",
      "index": 27,
      "name": null,
      "section_name": null,
      "segment_code": null,
      "segment_group_key": null,
      "segment_id": null,
      "value_pool_entry": null
    },
    {
      "ahb_expression": "Muss",
      "conditions": "",
      "data_element": null,
      "guid": "5240a5e3-7d95-406f-a9ba-2bbb6693dccf",
      "index": 28,
      "name": "",
      "section_name": "Produkt-/ Leistungsbeschreibung",
      "segment_code": "IMD",
      "segment_group_key": null,
      "segment_id": "00009",
      "value_pool_entry": null
    },
    {
      "ahb_expression": "X",
      "conditions": "",
      "data_element": "7081",
      "guid": "61ac91e9-43af-4c1b-ae5a-a9eaad9492cf",
      "index": 29,
      "name": "Angebot auf BasisPreisblatt",
      "section_name": "Produkt-/ Leistungsbeschreibung",
      "segment_code": "IMD",
      "segment_group_key": null,
      "segment_id": null,
      "value_pool_entry": "Z33"
    },
    {
      "ahb_expression": "X",
      "conditions": "",
      "data_element": "7081",
      "guid": "b45e9b7b-9dad-4d05-9da3-85621c9e1485",
      "index": 30,
      "name": "Individuelles Angebot",
      "section_name": "Produkt-/ Leistungsbeschreibung",
      "segment_code": "IMD",
      "segment_group_key": null,
      "segment_id": null,
      "value_pool_entry": "Z34"
    },
    {
      "ahb_expression": "Soll [17]",
      "conditions": null,
      "data_element": null,
      "guid": "54c8c971-ee99-45da-b659-d0683ef1eef5",
      "index": 31,
      "name": null,
      "section_name": null,
      "segment_code": null,
      "segment_group_key": "SG1",
      "segment_id": null,
      "value_pool_entry": null
    },
    {
      "ahb_expression": "Soll [17]",
      "conditions": "[17] Wenn das Angebot per REQOTE angefragt wurde",
      "data_element": null,
      "guid": "06eabf3d-d9ab-4246-9eea-3ffed9572b86",
      "index": 32,
      "name": "",
      "section_name": null,
      "segment_code": null,
      "segment_group_key": "SG1",
      "segment_id": null,
      "value_pool_entry": null
    },
    {
      "ahb_expression": "Muss",
      "conditions": "",
      "data_element": null,
      "guid": "1b0afa93-3b3f-4df2-9a2d-d5835fc87b74",
      "index": 33,
      "name": "",
      "section_name": "Nachrichtennummer der Anfrage",
      "segment_code": "RFF",
      "segment_group_key": "SG1",
      "segment_id": "00011",
      "value_pool_entry": null
    },
    {
      "ahb_expression": "X",
      "conditions": "",
      "data_element": "1153",
      "guid": "7fc36281-b62e-4b53-8120-f2567d97c5ca",
      "index": 34,
      "name": "Nummer der Anfrage",
      "section_name": "Nachrichtennummer der Anfrage",
      "segment_code": "RFF",
      "segment_group_key": "SG1",
      "segment_id": null,
      "value_pool_entry": "AAV"
    },
    {
      "ahb_expression": "X [505]",
      "conditions": "[505] Hinweis: Wert aus BGM+Z29 DE1004 der REQOTE, mit der die Anfrage Rechnungsabwicklung erfolgt ist.",
      "data_element": "1154",
      "guid": "c978b804-0fdc-4421-b18d-ec7f5ca5e93d",
      "index": 35,
      "name": "Nachrichtennummer",
      "section_name": "Nachrichtennummer der Anfrage",
      "segment_code": "RFF",
      "segment_group_key": "SG1",
      "segment_id": null,
      "value_pool_entry": null
    },
    {
      "ahb_expression": "Muss",
      "conditions": null,
      "data_element": null,
      "guid": "a0a5945b-b408-487f-ab66-482f90f606b6",
      "index": 36,
      "name": null,
      "section_name": null,
      "segment_code": null,
      "segment_group_key": "SG1",
      "segment_id": null,
      "value_pool_entry": null
    },
    {
      "ahb_expression": "Muss",
      "conditions": "",
      "data_element": null,
      "guid": "2d416714-143d-4c6e-9be6-efa0cce71b82",
      "index": 37,
      "name": "",
      "section_name": null,
      "segment_code": null,
      "segment_group_key": "SG1",
      "segment_id": null,
      "value_pool_entry": null
    },
    {
      "ahb_expression": "Muss",
      "conditions": "",
      "data_element": null,
      "guid": "948a257d-a567-4bd5-bf8b-8527b02d173f",
      "index": 38,
      "name": "",
      "section_name": "Prüfidentifikator",
      "segment_code": "RFF",
      "segment_group_key": "SG1",
      "segment_id": "00012",
      "value_pool_entry": null
    },
    {
      "ahb_expression": "X",
      "conditions": "",
      "data_element": "1153",
      "guid": "6dadb7ac-fc13-4895-ab0b-119a06186b14",
      "index": 39,
      "name": "Prüfidentifikator",
      "section_name": "Prüfidentifikator",
      "segment_code": "RFF",
      "segment_group_key": "SG1",
      "segment_id": null,
      "value_pool_entry": "Z13"
    },
    {
      "ahb_expression": "X",
      "conditions": "",
      "data_element": "1154",
      "guid": "4a1164a8-2048-4fe6-8e67-cf30e41f6904",
      "index": 40,
      "name": "AngebotRechnungsabwicklung MSBüber LF",
      "section_name": "Prüfidentifikator",
      "segment_code": "RFF",
      "segment_group_key": "SG1",
      "segment_id": null,
      "value_pool_entry": "15002"
    },
    {
      "ahb_expression": "Muss [21]",
      "conditions": null,
      "data_element": null,
      "guid": "902995ed-33d3-4add-bd8f-efc6deec08d0",
      "index": 41,
      "name": null,
      "section_name": null,
      "segment_code": null,
      "segment_group_key": "SG4",
      "segment_id": null,
      "value_pool_entry": null
    },
    {
      "ahb_expression": "Muss [21]",
      "conditions": "[21] Wenn IMD++Z34 vorhanden",
      "data_element": null,
      "guid": "c4a0d5b5-95fd-4c93-b728-28a7c59d6ae1",
      "index": 42,
      "name": "",
      "section_name": null,
      "segment_code": null,
      "segment_group_key": "SG4",
      "segment_id": null,
      "value_pool_entry": null
    },
    {
      "ahb_expression": "Muss",
      "conditions": "",
      "data_element": null,
      "guid": "2c3544e0-4124-495a-a797-950aad2415e4",
      "index": 43,
      "name": "",
      "section_name": "Währungsangaben",
      "segment_code": "CUX",
      "segment_group_key": "SG4",
      "segment_id": "00013",
      "value_pool_entry": null
    },
    {
      "ahb_expression": "X",
      "conditions": "",
      "data_element": "6347",
      "guid": "63d81bf7-f331-4314-a3a5-3e50dd4909bb",
      "index": 44,
      "name": "Referenzwährung",
      "section_name": "Währungsangaben",
      "segment_code": "CUX",
      "segment_group_key": "SG4",
      "segment_id": null,
      "value_pool_entry": "2"
    },
    {
      "ahb_expression": "X",
      "conditions": "",
      "data_element": "6345",
      "guid": "72528bbe-ff35-4ad3-ac7a-d19dfc2f8316",
      "index": 45,
      "name": "Euro",
      "section_name": "Währungsangaben",
      "segment_code": "CUX",
      "segment_group_key": "SG4",
      "segment_id": null,
      "value_pool_entry": "EUR"
    },
    {
      "ahb_expression": "X",
      "conditions": "",
      "data_element": "6343",
      "guid": "3022a157-ce66-441d-bb50-b115214e7035",
      "index": 46,
      "name": "Währung der Rechnung",
      "section_name": "Währungsangaben",
      "segment_code": "CUX",
      "segment_group_key": "SG4",
      "segment_id": null,
      "value_pool_entry": "4"
    },
    {
      "ahb_expression": "Muss",
      "conditions": null,
      "data_element": null,
      "guid": "88d21274-467b-4d54-8343-a4611aefad36",
      "index": 47,
      "name": null,
      "section_name": null,
      "segment_code": null,
      "segment_group_key": "SG11",
      "segment_id": null,
      "value_pool_entry": null
    },
    {
      "ahb_expression": "Muss",
      "conditions": "",
      "data_element": null,
      "guid": "509c26b1-1bee-495a-b556-49b768fceb94",
      "index": 48,
      "name": "",
      "section_name": null,
      "segment_code": null,
      "segment_group_key": "SG11",
      "segment_id": null,
      "value_pool_entry": null
    },
    {
      "ahb_expression": "Muss",
      "conditions": "",
      "data_element": null,
      "guid": "675c2c07-21be-475a-a981-f4e9ea30d388",
      "index": 49,
      "name": "",
      "section_name": "MP-ID Absender",
      "segment_code": "NAD",
      "segment_group_key": "SG11",
      "segment_id": "00014",
      "value_pool_entry": null
    },
    {
      "ahb_expression": "MS",
      "conditions": "",
      "data_element": "3035",
      "guid": "f022f315-5015-4a80-926a-93df589d295b",
      "index": 50,
      "name": "",
      "section_name": "MP-ID Absender",
      "segment_code": "NAD",
      "segment_group_key": "SG11",
      "segment_id": null,
      "value_pool_entry": "Nachrichtenaussteller bzw.-absender"
    },
    {
      "ahb_expression": "X [39]",
      "conditions": "[39] MP-ID nur aus Sparte Strom",
      "data_element": "3039",
      "guid": "59fd406a-b482-40fc-aab7-ae9904835d31",
      "index": 51,
      "name": "MP-ID",
      "section_name": "MP-ID Absender",
      "segment_code": "NAD",
      "segment_group_key": "SG11",
      "segment_id": null,
      "value_pool_entry": null
    },
    {
      "ahb_expression": "X",
      "conditions": "",
      "data_element": "3055",
      "guid": "69a56110-1491-4ab7-8d08-84d5ddb9ea1e",
      "index": 52,
      "name": "GS1",
      "section_name": "MP-ID Absender",
      "segment_code": "NAD",
      "segment_group_key": "SG11",
      "segment_id": null,
      "value_pool_entry": "9"
    },
    {
      "ahb_expression": "X",
      "conditions": "",
      "data_element": "3055",
      "guid": "6d62dc32-2a68-41f8-a1e9-82bbb83c2606",
      "index": 53,
      "name": "DE, BDEW (Bundesverbandder Energie- undWasserwirtschaft e.V.)",
      "section_name": "MP-ID Absender",
      "segment_code": "NAD",
      "segment_group_key": "SG11",
      "segment_id": null,
      "value_pool_entry": "293"
    },
    {
      "ahb_expression": "Muss",
      "conditions": null,
      "data_element": null,
      "guid": "db9b98e8-edfb-4e12-be63-59ec19793192",
      "index": 54,
      "name": null,
      "section_name": null,
      "segment_code": null,
      "segment_group_key": "SG14",
      "segment_id": null,
      "value_pool_entry": null
    },
    {
      "ahb_expression": "Muss",
      "conditions": "",
      "data_element": null,
      "guid": "e8a78fdf-47a8-40a7-a896-c68c1516fc95",
      "index": 55,
      "name": "",
      "section_name": null,
      "segment_code": null,
      "segment_group_key": "SG14",
      "segment_id": null,
      "value_pool_entry": null
    },
    {
      "ahb_expression": "Muss",
      "conditions": "",
      "data_element": null,
      "guid": "00b157bf-b770-4dfd-802d-d614758b13cc",
      "index": 56,
      "name": "",
      "section_name": "Ansprechpartner",
      "segment_code": "CTA",
      "segment_group_key": "SG14",
      "segment_id": "00015",
      "value_pool_entry": null
    },
    {
      "ahb_expression": "IC",
      "conditions": "",
      "data_element": "3139",
      "guid": "49754399-d837-4a2f-87fa-4a4cd9555f16",
      "index": 57,
      "name": "",
      "section_name": "Ansprechpartner",
      "segment_code": "CTA",
      "segment_group_key": "SG14",
      "segment_id": null,
      "value_pool_entry": null
    },
    {
      "ahb_expression": "X",
      "conditions": "",
      "data_element": "3412",
      "guid": "1bcedbea-47d0-4f6e-a5ca-94cb0e757b39",
      "index": 58,
      "name": "Kontakt",
      "section_name": "Ansprechpartner",
      "segment_code": "CTA",
      "segment_group_key": "SG14",
      "segment_id": null,
      "value_pool_entry": null
    },
    {
      "ahb_expression": null,
      "conditions": null,
      "data_element": null,
      "guid": "e9f04505-dd29-4844-9135-05058d7c9f1e",
      "index": 59,
      "name": null,
      "section_name": null,
      "segment_code": null,
      "segment_group_key": "SG14",
      "segment_id": null,
      "value_pool_entry": null
    },
    {
      "ahb_expression": "Muss",
      "conditions": null,
      "data_element": null,
      "guid": "7522ed91-e04f-4cfb-acc3-2c33e76d3256",
      "index": 60,
      "name": null,
      "section_name": null,
      "segment_code": null,
      "segment_group_key": "SG14",
      "segment_id": null,
      "value_pool_entry": null
    },
    {
      "ahb_expression": "Muss",
      "conditions": "",
      "data_element": null,
      "guid": "975fb179-47e3-4c80-9017-9d99ff7e21db",
      "index": 61,
      "name": "",
      "section_name": "Kommunikationsverbindung",
      "segment_code": "COM",
      "segment_group_key": "SG14",
      "segment_id": "00016",
      "value_pool_entry": null
    },
    {
      "ahb_expression": "X",
      "conditions": "",
      "data_element": "3148",
      "guid": "808bb894-a3d2-45c0-ba76-a67c9fbd91e2",
      "index": 62,
      "name": "Kommunikationsadresse,Identifikation",
      "section_name": "Kommunikationsverbindung",
      "segment_code": "COM",
      "segment_group_key": "SG14",
      "segment_id": null,
      "value_pool_entry": null
    },
    {
      "ahb_expression": "X [1P0..1]",
      "conditions": "",
      "data_element": "3155",
      "guid": "10353f14-0094-4cd2-b9a5-ca1f74e93997",
      "index": 63,
      "name": "Elektronische Post",
      "section_name": "Kommunikationsverbindung",
      "segment_code": "COM",
      "segment_group_key": "SG14",
      "segment_id": null,
      "value_pool_entry": "EM"
    },
    {
      "ahb_expression": "X [1P0..1]",
      "conditions": "",
      "data_element": "3155",
      "guid": "c5ae7055-7677-4d20-b3ee-d32ac438764d",
      "index": 64,
      "name": "Telefax",
      "section_name": "Kommunikationsverbindung",
      "segment_code": "COM",
      "segment_group_key": "SG14",
      "segment_id": null,
      "value_pool_entry": "FX"
    },
    {
      "ahb_expression": "Muss",
      "conditions": null,
      "data_element": null,
      "guid": "7ac28c3a-21c9-407c-a141-5b7248460590",
      "index": 65,
      "name": null,
      "section_name": null,
      "segment_code": null,
      "segment_group_key": "SG11",
      "segment_id": null,
      "value_pool_entry": null
    },
    {
      "ahb_expression": "Muss",
      "conditions": "",
      "data_element": null,
      "guid": "39f7eeee-6922-425b-8c8a-1ea625f1e8b8",
      "index": 66,
      "name": "",
      "section_name": null,
      "segment_code": null,
      "segment_group_key": "SG11",
      "segment_id": null,
      "value_pool_entry": null
    },
    {
      "ahb_expression": "Muss",
      "conditions": "",
      "data_element": null,
      "guid": "9d6c978d-eb35-4ddd-ae8d-5a721194678a",
      "index": 67,
      "name": "",
      "section_name": "MP-ID Empfänger",
      "segment_code": "NAD",
      "segment_group_key": "SG11",
      "segment_id": "00017",
      "value_pool_entry": null
    },
    {
      "ahb_expression": "MR",
      "conditions": "",
      "data_element": "3035",
      "guid": "13b2c72f-6e70-4c6c-8e6c-553045243721",
      "index": 68,
      "name": "",
      "section_name": "MP-ID Empfänger",
      "segment_code": "NAD",
      "segment_group_key": "SG11",
      "segment_id": null,
      "value_pool_entry": null
    },
    {
      "ahb_expression": "X [39]",
      "conditions": "[39] MP-ID nur aus Sparte Strom",
      "data_element": "3039",
      "guid": "00aede4e-134b-470e-9678-af415ab31173",
      "index": 69,
      "name": "MP-ID",
      "section_name": "MP-ID Empfänger",
      "segment_code": "NAD",
      "segment_group_key": "SG11",
      "segment_id": null,
      "value_pool_entry": null
    },
    {
      "ahb_expression": "X",
      "conditions": "",
      "data_element": "3055",
      "guid": "5e25e726-f2d4-4ab3-a91f-ca1807cf5290",
      "index": 70,
      "name": "GS1",
      "section_name": "MP-ID Empfänger",
      "segment_code": "NAD",
      "segment_group_key": "SG11",
      "segment_id": null,
      "value_pool_entry": "9"
    },
    {
      "ahb_expression": "X",
      "conditions": "",
      "data_element": "3055",
      "guid": "84731754-0a4e-4633-a2c4-f1a13c5db9de",
      "index": 71,
      "name": "DE, BDEW (Bundesverbandder Energie- undWasserwirtschaft e.V.)",
      "section_name": "MP-ID Empfänger",
      "segment_code": "NAD",
      "segment_group_key": "SG11",
      "segment_id": null,
      "value_pool_entry": "293"
    },
    {
      "ahb_expression": "Muss",
      "conditions": null,
      "data_element": null,
      "guid": "bc527f59-2603-42cb-ab63-0d347f988a59",
      "index": 72,
      "name": null,
      "section_name": null,
      "segment_code": null,
      "segment_group_key": "SG11",
      "segment_id": null,
      "value_pool_entry": null
    },
    {
      "ahb_expression": "Muss",
      "conditions": "",
      "data_element": null,
      "guid": "ce71aa24-73d1-4369-8308-0e780e4ba842",
      "index": 73,
      "name": "",
      "section_name": null,
      "segment_code": null,
      "segment_group_key": "SG11",
      "segment_id": null,
      "value_pool_entry": null
    },
    {
      "ahb_expression": "Muss",
      "conditions": "",
      "data_element": null,
      "guid": "950251f5-bd4c-43e4-92d4-b92e8c497b54",
      "index": 74,
      "name": "",
      "section_name": "Liefer-, bzw. Bezugsort",
      "segment_code": "NAD",
      "segment_group_key": "SG11",
      "segment_id": "00018",
      "value_pool_entry": null
    },
    {
      "ahb_expression": "DP",
      "conditions": "",
      "data_element": "3035",
      "guid": "d9b2d6f2-7a7c-41e5-85d7-4566fad96f90",
      "index": 75,
      "name": "",
      "section_name": "Liefer-, bzw. Bezugsort",
      "segment_code": "NAD",
      "segment_group_key": "SG11",
      "segment_id": null,
      "value_pool_entry": null
    },
    {
      "ahb_expression": null,
      "conditions": null,
      "data_element": null,
      "guid": "794fcb96-0014-43f9-ac88-b6f398091df9",
      "index": 76,
      "name": null,
      "section_name": null,
      "segment_code": null,
      "segment_group_key": "SG11",
      "segment_id": null,
      "value_pool_entry": null
    },
    {
      "ahb_expression": "Muss",
      "conditions": null,
      "data_element": null,
      "guid": "d5e07d94-4da0-4881-950f-5e449d033774",
      "index": 77,
      "name": null,
      "section_name": null,
      "segment_code": null,
      "segment_group_key": "SG11",
      "segment_id": null,
      "value_pool_entry": null
    },
    {
      "ahb_expression": "Muss",
      "conditions": "",
      "data_element": null,
      "guid": "39440536-0b8b-4bf2-ab9d-c1c4d36a173e",
      "index": 78,
      "name": "",
      "section_name": "Meldepunkt",
      "segment_code": "LOC",
      "segment_group_key": "SG11",
      "segment_id": "00019",
      "value_pool_entry": null
    },
    {
      "ahb_expression": "172",
      "conditions": "",
      "data_element": "3227",
      "guid": "f4f00e8f-b350-4377-a1c6-791cde9b6ddf",
      "index": 79,
      "name": "",
      "section_name": "Meldepunkt",
      "segment_code": "LOC",
      "segment_group_key": "SG11",
      "segment_id": null,
      "value_pool_entry": null
    },
    {
      "ahb_expression": "X [950] [501]",
      "conditions": "[501] Hinweis: Verwendung der ID der Marktlokation \n[950] Format: Marktlokations-ID",
      "data_element": "3225",
      "guid": "d2b55653-c7c6-48e8-90b5-09554b4d8436",
      "index": 80,
      "name": "Identifikator",
      "section_name": "Meldepunkt",
      "segment_code": "LOC",
      "segment_group_key": "SG11",
      "segment_id": null,
      "value_pool_entry": null
    },
    {
      "ahb_expression": "Muss",
      "conditions": null,
      "data_element": null,
      "guid": "1d52f029-9980-40db-94f3-dd83ebb64c7f",
      "index": 81,
      "name": null,
      "section_name": null,
      "segment_code": null,
      "segment_group_key": "SG27",
      "segment_id": null,
      "value_pool_entry": null
    },
    {
      "ahb_expression": "Muss",
      "conditions": "",
      "data_element": null,
      "guid": "6281a64a-fc43-4ab2-8cdb-319f58cb1ab7",
      "index": 82,
      "name": "",
      "section_name": null,
      "segment_code": null,
      "segment_group_key": "SG27",
      "segment_id": null,
      "value_pool_entry": null
    },
    {
      "ahb_expression": "Muss",
      "conditions": "",
      "data_element": null,
      "guid": "f14e660d-e582-44bd-9611-6002dbb2cd0f",
      "index": 83,
      "name": "",
      "section_name": "Positionsdaten",
      "segment_code": "LIN",
      "segment_group_key": "SG27",
      "segment_id": "00020",
      "value_pool_entry": null
    },
    {
      "ahb_expression": "X [911]",
      "conditions": "[911] Format: Mögliche Werte: 1 bis n, je Nachricht oder Segmentgruppe bei 1 beginnend und fortlaufend aufsteigend",
      "data_element": "1082",
      "guid": "94a6fbac-1270-4536-bb84-ffea6eb593b3",
      "index": 84,
      "name": "Positionsnummer",
      "section_name": "Positionsdaten",
      "segment_code": "LIN",
      "segment_group_key": "SG27",
      "segment_id": null,
      "value_pool_entry": null
    },
    {
      "ahb_expression": "X ([31] ∧ ([65] ⊻ [66])) ⊻([942] [69] ∧ ([67] ⊻ [68]))",
      "conditions": "[31] Es sind nur die Artikelnummern erlaubt, die in der Codeliste der Artikelnummern des BDEW mit dem entsprechenden Prüfidentifikator versehen sind. \n[65] Wenn DTM+203 (Ausführungsdatum) im DE2380 < 202312312300?+00 \n[66] Wenn DTM+469 (Beginn zum (nächstmöglichen Termin)) im DE2380 < 202312312300?+00 \n[67] Wenn DTM+203 (Ausführungsdatum) im DE2380 ≥ 202312312300?+00 \n[68] Wenn DTM+469 (Beginn zum (nächstmöglichen Termin)) im DE2380 ≥ 202312312300?+00 \n[69] Es sind nur Werte aus der EDI@Energy Codeliste der Artikelnummern und Artikel-ID erlaubt, die im Kapitel 3.5",
      "data_element": "7140",
      "guid": "2abf7669-f06a-4e73-8dee-d6149096dd90",
      "index": 85,
      "name": "Produkt-/Leistungsnummer",
      "section_name": "Positionsdaten",
      "segment_code": "LIN",
      "segment_group_key": "SG27",
      "segment_id": null,
      "value_pool_entry": null
    },
    {
      "ahb_expression": "X [65] ⊻ [66]",
      "conditions": "",
      "data_element": "7143",
      "guid": "03fad2e4-20e7-419f-b44c-2c5fd05a30a7",
      "index": 86,
      "name": "Artikelnummer",
      "section_name": "Positionsdaten",
      "segment_code": "LIN",
      "segment_group_key": "SG27",
      "segment_id": null,
      "value_pool_entry": "Z01"
    },
    {
      "ahb_expression": "X [67] ⊻ [68]",
      "conditions": "[65] Wenn DTM+203 (Ausführungsdatum) im DE2380 < 202312312300?+00 \n[66] Wenn DTM+469 (Beginn zum (nächstmöglichen Termin)) im DE2380 < 202312312300?+00 \n[67] Wenn DTM+203 (Ausführungsdatum) im DE2380 ≥ 202312312300?+00 \n[68] Wenn DTM+469 (Beginn zum (nächstmöglichen Termin)) im DE2380 ≥ 202312312300?+00",
      "data_element": "7143",
      "guid": "b0e39916-940d-47b1-aef0-9d5132f675e6",
      "index": 87,
      "name": "Artikel-ID",
      "section_name": "Positionsdaten",
      "segment_code": "LIN",
      "segment_group_key": "SG27",
      "segment_id": null,
      "value_pool_entry": "Z09"
    },
    {
      "ahb_expression": null,
      "conditions": null,
      "data_element": null,
      "guid": "17718807-cc29-43b3-ae2d-3967a2c0e4f0",
      "index": 88,
      "name": null,
      "section_name": null,
      "segment_code": null,
      "segment_group_key": "SG27",
      "segment_id": null,
      "value_pool_entry": null
    },
    {
      "ahb_expression": "Muss [20] ∧ ([65] ⊻ [66])",
      "conditions": null,
      "data_element": null,
      "guid": "129ce56b-5335-4217-9847-14eb222faac8",
      "index": 89,
      "name": null,
      "section_name": null,
      "segment_code": null,
      "segment_group_key": "SG27",
      "segment_id": null,
      "value_pool_entry": null
    },
    {
      "ahb_expression": "Muss [20] ∧ ([65] ⊻ [66])",
      "conditions": "[20] Wenn IMD++Z33 vorhanden \n[65] Wenn DTM+203 (Ausführungsdatum) im DE2380 < 202312312300?+00 \n[66] Wenn DTM+469 (Beginn zum (nächstmöglichen Termin)) im DE2380 < 202312312300?+00",
      "data_element": null,
      "guid": "de0c737c-7d98-4307-9b11-9e225c6b0b79",
      "index": 90,
      "name": "",
      "section_name": "Zusätzliche Produktidentifikation",
      "segment_code": "PIA",
      "segment_group_key": "SG27",
      "segment_id": "00021",
      "value_pool_entry": null
    },
    {
      "ahb_expression": "1",
      "conditions": "",
      "data_element": "4347",
      "guid": "eeb4519f-2d31-4359-8dcc-69cc4f6adabc",
      "index": 91,
      "name": "",
      "section_name": "Zusätzliche Produktidentifikation",
      "segment_code": "PIA",
      "segment_group_key": "SG27",
      "segment_id": null,
      "value_pool_entry": null
    },
    {
      "ahb_expression": "X",
      "conditions": "",
      "data_element": "7140",
      "guid": "67331ecb-8b43-460f-b45b-174fe9026233",
      "index": 92,
      "name": "Preisschlüsselstamm",
      "section_name": "Zusätzliche Produktidentifikation",
      "segment_code": "PIA",
      "segment_group_key": "SG27",
      "segment_id": null,
      "value_pool_entry": null
    },
    {
      "ahb_expression": "X",
      "conditions": "",
      "data_element": "7143",
      "guid": "c73d94a9-1dec-4132-9b13-a909ad725dd0",
      "index": 93,
      "name": "Preisschlüsselstamm",
      "section_name": "Zusätzliche Produktidentifikation",
      "segment_code": "PIA",
      "segment_group_key": "SG27",
      "segment_id": null,
      "value_pool_entry": "Z06"
    },
    {
      "ahb_expression": null,
      "conditions": null,
      "data_element": null,
      "guid": "8d16a417-7458-4cc5-b0c1-c8377620edaa",
      "index": 94,
      "name": null,
      "section_name": null,
      "segment_code": null,
      "segment_group_key": "SG27",
      "segment_id": null,
      "value_pool_entry": null
    },
    {
      "ahb_expression": "Muss",
      "conditions": null,
      "data_element": null,
      "guid": "e9cf72b2-dd25-4429-a3c4-95dbc45c3c6d",
      "index": 95,
      "name": null,
      "section_name": null,
      "segment_code": null,
      "segment_group_key": "SG27",
      "segment_id": null,
      "value_pool_entry": null
    },
    {
      "ahb_expression": "Muss",
      "conditions": "",
      "data_element": null,
      "guid": "843bad53-f7f3-4b9e-bfee-23d954ea7c6e",
      "index": 96,
      "name": "",
      "section_name": "Menge",
      "segment_code": "QTY",
      "segment_group_key": "SG27",
      "segment_id": "00023",
      "value_pool_entry": null
    },
    {
      "ahb_expression": "X",
      "conditions": "",
      "data_element": "6063",
      "guid": "fcd31f0f-a13d-4416-9923-a3e78ebf5af4",
      "index": 97,
      "name": "Berechnete (fakturierte)Menge",
      "section_name": "Menge",
      "segment_code": "QTY",
      "segment_group_key": "SG27",
      "segment_id": null,
      "value_pool_entry": "47"
    },
    {
      "ahb_expression": "X [908]",
      "conditions": "[908] Format: Mögliche Werte: 1 bis n",
      "data_element": "6060",
      "guid": "fa9fbb20-5824-4a5a-9926-be795c6770b7",
      "index": 98,
      "name": "Menge",
      "section_name": "Menge",
      "segment_code": "QTY",
      "segment_group_key": "SG27",
      "segment_id": null,
      "value_pool_entry": null
    },
    {
      "ahb_expression": "X",
      "conditions": "",
      "data_element": "6411",
      "guid": "c77b395a-0b3a-4fff-9e70-8fbc79da60d2",
      "index": 99,
      "name": "Stück",
      "section_name": "Menge",
      "segment_code": "QTY",
      "segment_group_key": "SG27",
      "segment_id": null,
      "value_pool_entry": "H87"
    },
    {
      "ahb_expression": null,
      "conditions": null,
      "data_element": null,
      "guid": "88fbf069-2ad1-4858-8c45-3f95052593f2",
      "index": 100,
      "name": null,
      "section_name": null,
      "segment_code": null,
      "segment_group_key": "SG27",
      "segment_id": null,
      "value_pool_entry": null
    },
    {
      "ahb_expression": "Muss [21]",
      "conditions": null,
      "data_element": null,
      "guid": "cd7761b1-9227-43a3-a04a-8b82d56810a5",
      "index": 101,
      "name": null,
      "section_name": null,
      "segment_code": null,
      "segment_group_key": "SG27",
      "segment_id": null,
      "value_pool_entry": null
    },
    {
      "ahb_expression": "Muss [21]",
      "conditions": "[21] Wenn IMD++Z34 vorhanden",
      "data_element": null,
      "guid": "a584803f-3690-412d-9cc1-c2fc28181eaf",
      "index": 102,
      "name": "",
      "section_name": "zeitliche Mengenangaben",
      "segment_code": "QTY",
      "segment_group_key": "SG27",
      "segment_id": "00024",
      "value_pool_entry": null
    },
    {
      "ahb_expression": "X",
      "conditions": "",
      "data_element": "6063",
      "guid": "f726eb2b-3f7c-43da-8af5-75bd7d576d42",
      "index": 103,
      "name": "Erreichte Menge in demZeitintervall",
      "section_name": "zeitliche Mengenangaben",
      "segment_code": "QTY",
      "segment_group_key": "SG27",
      "segment_id": null,
      "value_pool_entry": "136"
    },
    {
      "ahb_expression": "X [908]",
      "conditions": "[908] Format: Mögliche Werte: 1 bis n",
      "data_element": "6060",
      "guid": "66b87337-7f8d-4915-ae02-dba38d103ac2",
      "index": 104,
      "name": "Menge",
      "section_name": "zeitliche Mengenangaben",
      "segment_code": "QTY",
      "segment_group_key": "SG27",
      "segment_id": null,
      "value_pool_entry": null
    },
    {
      "ahb_expression": "X",
      "conditions": "",
      "data_element": "6411",
      "guid": "4326e018-f1ee-4d40-a45f-2e83b40834d6",
      "index": 105,
      "name": "Jahr",
      "section_name": "zeitliche Mengenangaben",
      "segment_code": "QTY",
      "segment_group_key": "SG27",
      "segment_id": null,
      "value_pool_entry": "ANN"
    },
    {
      "ahb_expression": "X",
      "conditions": "",
      "data_element": "6411",
      "guid": "dd5e9120-ee9f-46e2-87b5-8813c6806cdb",
      "index": 106,
      "name": "Tag",
      "section_name": "zeitliche Mengenangaben",
      "segment_code": "QTY",
      "segment_group_key": "SG27",
      "segment_id": null,
      "value_pool_entry": "DAY"
    },
    {
      "ahb_expression": "X",
      "conditions": "",
      "data_element": "6411",
      "guid": "100aab4c-ee4f-47b2-86a4-cfdd11215455",
      "index": 107,
      "name": "Monat",
      "section_name": "zeitliche Mengenangaben",
      "segment_code": "QTY",
      "segment_group_key": "SG27",
      "segment_id": null,
      "value_pool_entry": "MON"
    },
    {
      "ahb_expression": "Muss [21]",
      "conditions": null,
      "data_element": null,
      "guid": "e03173ff-fe19-42f7-990c-7f3bc2ce9c14",
      "index": 108,
      "name": null,
      "section_name": null,
      "segment_code": null,
      "segment_group_key": "SG29",
      "segment_id": null,
      "value_pool_entry": null
    },
    {
      "ahb_expression": "Muss [21]",
      "conditions": "[21] Wenn IMD++Z34 vorhanden",
      "data_element": null,
      "guid": "1ba58641-c278-4783-9893-94203102dce5",
      "index": 109,
      "name": "",
      "section_name": null,
      "segment_code": null,
      "segment_group_key": "SG29",
      "segment_id": null,
      "value_pool_entry": null
    },
    {
      "ahb_expression": "Muss",
      "conditions": "",
      "data_element": null,
      "guid": "44e2cca4-5fb1-45e5-81e1-6b85d4237069",
      "index": 110,
      "name": "",
      "section_name": "Geldbetrag",
      "segment_code": "MOA",
      "segment_group_key": "SG29",
      "segment_id": "00048",
      "value_pool_entry": null
    },
    {
      "ahb_expression": "X",
      "conditions": "",
      "data_element": "5025",
      "guid": "a760d91d-c155-4c91-8f08-bbce8f3362ba",
      "index": 111,
      "name": "Positionsbetrag (ohne USt.)",
      "section_name": "Geldbetrag",
      "segment_code": "MOA",
      "segment_group_key": "SG29",
      "segment_id": null,
      "value_pool_entry": "203"
    },
    {
      "ahb_expression": "X [930]",
      "conditions": "[930] Format: max. 2 Nachkommastellen",
      "data_element": "5004",
      "guid": "2d033ffe-ef85-4198-bbf9-f3308b36cc36",
      "index": 112,
      "name": "Geldbetrag",
      "section_name": "Geldbetrag",
      "segment_code": "MOA",
      "segment_group_key": "SG29",
      "segment_id": null,
      "value_pool_entry": null
    },
    {
      "ahb_expression": "Muss [21]",
      "conditions": null,
      "data_element": null,
      "guid": "eefc7f5a-a3ab-4797-87ee-0098f96040bc",
      "index": 113,
      "name": null,
      "section_name": null,
      "segment_code": null,
      "segment_group_key": "SG31",
      "segment_id": null,
      "value_pool_entry": null
    },
    {
      "ahb_expression": "Muss [21]",
      "conditions": "[21] Wenn IMD++Z34 vorhanden",
      "data_element": null,
      "guid": "825e9901-08f5-465d-9a9c-07796dccbc3e",
      "index": 114,
      "name": "",
      "section_name": null,
      "segment_code": null,
      "segment_group_key": "SG31",
      "segment_id": null,
      "value_pool_entry": null
    },
    {
      "ahb_expression": "Muss",
      "conditions": "",
      "data_element": null,
      "guid": "a93c09f3-35ef-471a-acf2-0e16a1f11a0e",
      "index": 115,
      "name": "",
      "section_name": "Preisangaben",
      "segment_code": "PRI",
      "segment_group_key": "SG31",
      "segment_id": "00049",
      "value_pool_entry": null
    },
    {
      "ahb_expression": "X",
      "conditions": "",
      "data_element": "5125",
      "guid": "a667dde6-fc42-4a56-b8f1-44ecc5e8e3d8",
      "index": 116,
      "name": "Berechnungspreis",
      "section_name": "Preisangaben",
      "segment_code": "PRI",
      "segment_group_key": "SG31",
      "segment_id": null,
      "value_pool_entry": "CAL"
    },
    {
      "ahb_expression": "X [912]",
      "conditions": "[912] Format: max. 6 Nachkommastellen",
      "data_element": "5118",
      "guid": "bcc3b435-7afa-4e79-bc60-34b7fb5f7d1b",
      "index": 117,
      "name": "Preis, Betrag",
      "section_name": "Preisangaben",
      "segment_code": "PRI",
      "segment_group_key": "SG31",
      "segment_id": null,
      "value_pool_entry": null
    },
    {
      "ahb_expression": "Soll [18] ∧ [20]",
      "conditions": null,
      "data_element": null,
      "guid": "596e6c93-b4c5-4154-83a2-5e41bc4c0313",
      "index": 118,
      "name": null,
      "section_name": null,
      "segment_code": null,
      "segment_group_key": "SG32",
      "segment_id": null,
      "value_pool_entry": null
    },
    {
      "ahb_expression": "Soll [18] ∧ [20]",
      "conditions": "[18] Wenn Angebot mehrere Marktlokationen abdeckt (AN nutzt mehrere Marktlokationen in einem Gebäude) \n[20] Wenn IMD++Z33 vorhanden",
      "data_element": null,
      "guid": "6e2ae5e2-3a54-4a01-9694-ebd807d866da",
      "index": 119,
      "name": "",
      "section_name": null,
      "segment_code": null,
      "segment_group_key": "SG32",
      "segment_id": null,
      "value_pool_entry": null
    },
    {
      "ahb_expression": "Muss",
      "conditions": "",
      "data_element": null,
      "guid": "b2069ef6-d4a7-4bdb-9d00-8a3a9437e542",
      "index": 120,
      "name": "",
      "section_name": "Referenz auf ID weiterer Marktlokationen",
      "segment_code": "RFF",
      "segment_group_key": "SG32",
      "segment_id": "00051",
      "value_pool_entry": null
    },
    {
      "ahb_expression": "X",
      "conditions": "",
      "data_element": "1153",
      "guid": "a3541a58-2046-4e4a-92a8-263bced8fcef",
      "index": 121,
      "name": "Marktlokation",
      "section_name": "Referenz auf ID weiterer Marktlokationen",
      "segment_code": "RFF",
      "segment_group_key": "SG32",
      "segment_id": null,
      "value_pool_entry": "Z18"
    },
    {
      "ahb_expression": "X [950]",
      "conditions": "[950] Format: Marktlokations-ID",
      "data_element": "1154",
      "guid": "b3dc70f9-7979-4411-9ba3-2caa4e15a7fb",
      "index": 122,
      "name": "ID einer Marktlokation",
      "section_name": "Referenz auf ID weiterer Marktlokationen",
      "segment_code": "RFF",
      "segment_group_key": "SG32",
      "segment_id": null,
      "value_pool_entry": null
    },
    {
      "ahb_expression": "Muss",
      "conditions": null,
      "data_element": null,
      "guid": "ab45ff8c-d769-47e1-993f-c4b5cd6b81cd",
      "index": 123,
      "name": null,
      "section_name": null,
      "segment_code": null,
      "segment_group_key": null,
      "segment_id": null,
      "value_pool_entry": null
    },
    {
      "ahb_expression": "Muss",
      "conditions": "",
      "data_element": null,
      "guid": "5643e52a-6afe-4b99-85e7-9a43b14cb9e4",
      "index": 124,
      "name": "",
      "section_name": "Abschnitts-Kontrollsegment",
      "segment_code": "UNS",
      "segment_group_key": null,
      "segment_id": "00097",
      "value_pool_entry": null
    },
    {
      "ahb_expression": "S",
      "conditions": "",
      "data_element": "0081",
      "guid": "14c4ea98-7ad0-467c-a448-e1243da727f4",
      "index": 125,
      "name": "",
      "section_name": "Abschnitts-Kontrollsegment",
      "segment_code": "UNS",
      "segment_group_key": null,
      "segment_id": null,
      "value_pool_entry": "und Summenteil"
    },
    {
      "ahb_expression": "Muss [21]",
      "conditions": null,
      "data_element": null,
      "guid": "9335f5e9-d75e-4e3c-88b6-7407814536df",
      "index": 126,
      "name": null,
      "section_name": null,
      "segment_code": null,
      "segment_group_key": null,
      "segment_id": null,
      "value_pool_entry": null
    },
    {
      "ahb_expression": "Muss [21]",
      "conditions": "[21] Wenn IMD++Z34 vorhanden",
      "data_element": null,
      "guid": "3533f8b3-93c6-494b-9bc3-b2506fbb11cc",
      "index": 127,
      "name": "",
      "section_name": "Summenbetrag (netto)",
      "segment_code": "MOA",
      "segment_group_key": null,
      "segment_id": "00098",
      "value_pool_entry": null
    },
    {
      "ahb_expression": "X",
      "conditions": "",
      "data_element": "5025",
      "guid": "e5c9b961-1068-4181-a206-e138ef69ff2a",
      "index": 128,
      "name": "Gesamtbetrag desAngebots",
      "section_name": "Summenbetrag (netto)",
      "segment_code": "MOA",
      "segment_group_key": null,
      "segment_id": null,
      "value_pool_entry": "97"
    },
    {
      "ahb_expression": "X [930]",
      "conditions": "[930] Format: max. 2 Nachkommastellen",
      "data_element": "5004",
      "guid": "f4e19a03-ac98-4a7a-a73f-013ad9444bab",
      "index": 129,
      "name": "Geldbetrag",
      "section_name": "Summenbetrag (netto)",
      "segment_code": "MOA",
      "segment_group_key": null,
      "segment_id": null,
      "value_pool_entry": null
    },
    {
      "ahb_expression": "Muss",
      "conditions": null,
      "data_element": null,
      "guid": "1a739752-6fae-452f-b1c9-382e1c4d8722",
      "index": 130,
      "name": null,
      "section_name": null,
      "segment_code": null,
      "segment_group_key": null,
      "segment_id": null,
      "value_pool_entry": null
    },
    {
      "ahb_expression": "Muss",
      "conditions": "",
      "data_element": null,
      "guid": "1f97f0d8-ad0e-4ef1-a646-53da5546feca",
      "index": 131,
      "name": "",
      "section_name": "Nachrichten-Endesegment",
      "segment_code": "UNT",
      "segment_group_key": null,
      "segment_id": "00099",
      "value_pool_entry": null
    },
    {
      "ahb_expression": "X",
      "conditions": "",
      "data_element": "0074",
      "guid": "e5d895dc-524c-4327-8e9d-dffc05be2ac3",
      "index": 132,
      "name": "Anzahl der Segmente in einerNachricht",
      "section_name": "Nachrichten-Endesegment",
      "segment_code": "UNT",
      "segment_group_key": null,
      "segment_id": null,
      "value_pool_entry": null
    },
    {
      "ahb_expression": "X",
      "conditions": "",
      "data_element": "0062",
      "guid": "154951f3-c9c4-417f-9284-93729d2c03db",
      "index": 133,
      "name": "Nachrichten-Referenznummer",
      "section_name": "Nachrichten-Endesegment",
      "segment_code": "UNT",
      "segment_group_key": null,
      "segment_id": null,
      "value_pool_entry": null
    }
  ],
  "meta": {
    "description": "QUOTES Angebot zur Abrechnung des Messstellenbetriebs vom MSB an den LF",
    "direction": "MSB an LF",
    "maus_version": "0.3.0",
    "pruefidentifikator": "15002"
  }
}
